aleksis/apps/cursus/__init__.py
aleksis/apps/cursus/apps.py
aleksis/apps/cursus/frontend/components/Course.vue
aleksis/apps/cursus/frontend/components/CourseBundle.vue
aleksis/apps/cursus/frontend/components/CreateCourse.vue
aleksis/apps/cursus/frontend/components/CreateCourseBundle.vue
aleksis/apps/cursus/frontend/components/CreateSubject.vue
aleksis/apps/cursus/frontend/components/SchoolStructure.vue
aleksis/apps/cursus/frontend/components/Subject.vue
aleksis/apps/cursus/frontend/components/SubjectChip.vue
aleksis/apps/cursus/frontend/components/SubjectChipSelectField.vue
aleksis/apps/cursus/frontend/components/SubjectField.vue
aleksis/apps/cursus/frontend/components/TeacherField.vue
aleksis/apps/cursus/frontend/components/course.graphql
aleksis/apps/cursus/frontend/components/courseBundle.graphql
aleksis/apps/cursus/frontend/components/courseBundleFieldsMixin.js
aleksis/apps/cursus/frontend/components/helper.graphql
aleksis/apps/cursus/frontend/components/schoolStructure.graphql
aleksis/apps/cursus/frontend/components/subject.graphql
aleksis/apps/cursus/frontend/index.js
aleksis/apps/cursus/frontend/messages/ar.json
aleksis/apps/cursus/frontend/messages/de.json
aleksis/apps/cursus/frontend/messages/en.json
aleksis/apps/cursus/frontend/messages/fr.json
aleksis/apps/cursus/frontend/messages/la.json
aleksis/apps/cursus/frontend/messages/nb_NO.json
aleksis/apps/cursus/frontend/messages/ru.json
aleksis/apps/cursus/frontend/messages/tr.json
aleksis/apps/cursus/frontend/messages/uk.json
aleksis/apps/cursus/locale/.keepdir
aleksis/apps/cursus/locale/ar/LC_MESSAGES/django.mo
aleksis/apps/cursus/locale/ar/LC_MESSAGES/django.po
aleksis/apps/cursus/locale/de_DE/LC_MESSAGES/django.mo
aleksis/apps/cursus/locale/de_DE/LC_MESSAGES/django.po
aleksis/apps/cursus/locale/fr/LC_MESSAGES/django.mo
aleksis/apps/cursus/locale/fr/LC_MESSAGES/django.po
aleksis/apps/cursus/locale/la/LC_MESSAGES/django.mo
aleksis/apps/cursus/locale/la/LC_MESSAGES/django.po
aleksis_app_cursus-1.0.1.dist-info/LICENCE.rst
aleksis_app_cursus-1.0.1.dist-info/METADATA
aleksis_app_cursus-1.0.1.dist-info/WHEEL
aleksis_app_cursus-1.0.1.dist-info/entry_points.txt
aleksis_app_cursus-1.0.1.dist-info/RECORD
